pyDBA/Conf.py
pyDBA/DBAccess.py
pyDBA/Model.py
pyDBA/Nidus.py
pyDBA/Report.py
pyDBA/Role.py
pyDBA/Series.py
pyDBA/User.py
pyDBA/__init__.py
pyDBA/mongoEng.py
pyDBA/pymongoTest.py
pyDBA/test2.py
pyDBA/utils.py
bcm_db_opt-0.1.0.dist-info/METADATA
bcm_db_opt-0.1.0.dist-info/WHEEL
bcm_db_opt-0.1.0.dist-info/top_level.txt
bcm_db_opt-0.1.0.dist-info/RECORD
